LICENSE
MANIFEST.in
README.md
setup.py
demobambu/__init__.py
demobambu/api_helper.py
demobambu/configuration.py
demobambu/decorators.py
demobambu/demobambu_client.py
demobambu.egg-info/PKG-INFO
demobambu.egg-info/SOURCES.txt
demobambu.egg-info/dependency_links.txt
demobambu.egg-info/requires.txt
demobambu.egg-info/top_level.txt
demobambu/controllers/__init__.py
demobambu/controllers/base_controller.py
demobambu/controllers/misc_controller.py
demobambu/exceptions/__init__.py
demobambu/exceptions/api_exception.py
demobambu/http/__init__.py
demobambu/http/http_call_back.py
demobambu/http/http_client.py
demobambu/http/http_context.py
demobambu/http/http_method_enum.py
demobambu/http/http_request.py
demobambu/http/http_response.py
demobambu/http/requests_client.py
demobambu/models/__init__.py
tests/__init__.py
tests/http_response_catcher.py
tests/test_helper.py
tests/controllers/__init__.py
tests/controllers/controller_test_base.py
tests/controllers/test_misc_controller.py