Metadata-Version: 1.0
Name: demobambu
Version: 1.11
Summary: TODO: Add Description
Home-page: https://apimatic.io
Author: APIMatic SDK Generator
Author-email: support@apimatic.io
License: UNKNOWN
Platform: UNKNOWN
